coastalimagelib/argusIO.py
coastalimagelib/argusIO_v2.py
coastalimagelib/corefunctions.py
coastalimagelib/supportfunctions.py
coastalimagelib-1.1.0.dist-info/LICENSE
coastalimagelib-1.1.0.dist-info/METADATA
coastalimagelib-1.1.0.dist-info/WHEEL
coastalimagelib-1.1.0.dist-info/top_level.txt
coastalimagelib-1.1.0.dist-info/RECORD
