Metadata-Version: 2.1
Name: coastalimagelib
Version: 1.1.0
Summary: Package for creating coastal image products.
Home-page: https://github.com/mailemccann/coastalimagelib
Author: Maile P. McCann
Author-email: mailemcc@usc.ed
License: MIT
License-File: LICENSE
Requires-Dist: imageio
Requires-Dist: matplotlib
Requires-Dist: numpy
Requires-Dist: opencv-python
Requires-Dist: jupyter
Requires-Dist: ipykernel
Requires-Dist: scikit-image
Requires-Dist: scipy
Requires-Dist: scikit-learn
Requires-Dist: netCDF4
Requires-Dist: multiprocess
Requires-Dist: xarray
